pweb_form_rest/__init__.py
pweb_form_rest/pweb_fr.py
pweb_form_rest/common/__init__.py
pweb_form_rest/common/pweb_com_fr_message.py
pweb_form_rest/common/pweb_custom_field.py
pweb_form_rest/common/pweb_fr_config.py
pweb_form_rest/common/pweb_fr_constant.py
pweb_form_rest/common/pweb_fr_exception.py
pweb_form_rest/common/pweb_vexception_handler.py
pweb_form_rest/common/pweb_web_file_util.py
pweb_form_rest/crud/__init__.py
pweb_form_rest/crud/pweb_crud.py
pweb_form_rest/crud/pweb_crud_common.py
pweb_form_rest/crud/pweb_file_data_crud.py
pweb_form_rest/crud/pweb_form_data_crud.py
pweb_form_rest/crud/pweb_request_data.py
pweb_form_rest/crud/pweb_response_maker.py
pweb_form_rest/crud/pweb_rest_data_crud.py
pweb_form_rest/crud/pweb_upload_processor.py
pweb_form_rest/data/__init__.py
pweb_form_rest/data/pweb_request_info.py
pweb_form_rest/data/pweb_response_data.py
pweb_form_rest/data/pweb_response_status.py
pweb_form_rest/form/__init__.py
pweb_form_rest/form/pweb_form.py
pweb_form_rest/form/pweb_form_data.py
pweb_form_rest/form/pweb_form_definition.py
pweb_form_rest/form/pweb_form_field.py
pweb_form_rest/form/pweb_process_form_field.py
pweb_form_rest/schema/__init__.py
pweb_form_rest/schema/pweb_rest_schema.py
pweb_form_rest/swagger/__init__.py
pweb_form_rest/swagger/pweb_sd_processor.py
pweb_form_rest/swagger/pweb_swagger_decorator.py
pweb_form_rest/swagger/pweb_swagger_generator.py
pweb_form_rest/swagger/pweb_swagger_param_def.py
pweb_form_rest/swagger/pweb_swagger_schema.py
pweb_form_rest/swagger/pweb_swagger_ui.py
pweb_form_rest/swagger/template-assets/assets/css/swagger-ui.css
pweb_form_rest/swagger/template-assets/assets/js/swagger-ui-bundle.js
pweb_form_rest/swagger/template-assets/assets/js/swagger-ui-standalone-preset.js
pweb_form_rest/swagger/template-assets/templates/pweb-swagger-ui.html
pweb_form_rest/ui/__init__.py
pweb_form_rest/ui/pweb_ui_helper.py
pweb_form_rest-0.0.11.dist-info/LICENSE
pweb_form_rest-0.0.11.dist-info/METADATA
pweb_form_rest-0.0.11.dist-info/WHEEL
pweb_form_rest-0.0.11.dist-info/top_level.txt
pweb_form_rest-0.0.11.dist-info/RECORD
