Metadata-Version: 2.1
Name: pweb-form-rest
Version: 0.0.11
Summary: Make Form & REST API convention, Validate request and produce response for PWeb application. It can produce Swagger API Documentation as well
Home-page: https://github.com/banglafighter/pweb-form-rest
Author: Bangla Fighter
Author-email: banglafighter.com@gmail.com
License: Apache 2.0
Platform: any
Classifier: Intended Audience :: Developers
Classifier: License :: OSI Approved :: Apache Software License
Classifier: Programming Language :: Python
License-File: LICENSE
Requires-Dist: marshmallow ==3.20.1
Requires-Dist: apispec ==6.3.0
Requires-Dist: marshmallow-sqlalchemy
Requires-Dist: ppy-common
Requires-Dist: pweb-orm
Requires-Dist: ppy-file-text
